rs_bpe-0.1.0.dist-info/METADATA
rs_bpe-0.1.0.dist-info/WHEEL
rs_bpe-0.1.0.dist-info/licenses/LICENSE
rs_bpe/__init__.py
rs_bpe/openai.py
rs_bpe/py.typed
rs_bpe/bpe.cpython-313-darwin.so
rs_bpe-0.1.0.dist-info/RECORD
