Metadata-Version: 2.4
Name: rs_bpe
Version: 0.1.0
Classifier: Development Status :: 5 - Production/Stable
Classifier: Intended Audience :: Developers
Classifier: Intended Audience :: Science/Research
Classifier: License :: OSI Approved :: MIT License
Classifier: Operating System :: OS Independent
Classifier: Programming Language :: Python :: Implementation :: CPython
Classifier: Programming Language :: Python :: Implementation :: PyPy
Classifier: Programming Language :: Python :: 3
Classifier: Programming Language :: Python :: 3.8
Classifier: Programming Language :: Python :: 3.9
Classifier: Programming Language :: Python :: 3.10
Classifier: Programming Language :: Python :: 3.11
Classifier: Programming Language :: Python :: 3.12
Classifier: Programming Language :: Python :: 3.13
Classifier: Programming Language :: Rust
Classifier: Topic :: Scientific/Engineering :: Artificial Intelligence
Classifier: Topic :: Text Processing :: Linguistic
Classifier: Typing :: Typed
Requires-Dist: maturin>=1.8.3 ; extra == 'dev'
Requires-Dist: tomli>=2.2.1 ; extra == 'dev'
Requires-Dist: mypy>=1.15.0 ; extra == 'dev'
Requires-Dist: ruff>=0.11.0 ; extra == 'dev'
Requires-Dist: numpy>=2.2.4 ; extra == 'benchmark'
Requires-Dist: matplotlib>=3.10.1 ; extra == 'benchmark'
Requires-Dist: scikit-learn>=1.6.1 ; extra == 'benchmark'
Requires-Dist: tiktoken>=0.9.0 ; extra == 'benchmark'
Requires-Dist: tokenizers>=0.21.0 ; extra == 'benchmark'
Requires-Dist: pytest>=8.3.5 ; extra == 'test'
Provides-Extra: dev
Provides-Extra: benchmark
Provides-Extra: test
License-File: LICENSE
Summary: A ridiculously fast Python BPE (Byte Pair Encoder) implementation written in Rust
Keywords: byte-pair-encoding,subword-tokenization,subword-units,tokenization,tokenizer,vocabulary,vocab,text-encoding,text-processing,string-encoding,rust,rust-extension,cpython-extension,python-library,python-package,pypi,cross-platform,fast,performance,high-performance,efficient,optimized,speed,blazing-fast,rapid,accelerated,nlp,natural-language-processing,machine-learning,deep-learning,artificial-intelligence,ai,llm,large-language-models,transformers,generative-ai,text-generation,embeddings,d
Author: gweidart <gweidart@gmail.com>
Author-email: gweidart <gweidart@gmail.com>
License: MIT
Requires-Python: >=3.8
Project-URL: Homepage, https://github.com/gweidart/rs-bpe
Project-URL: Repository, https://github.com/gweidart/rs-bpe
Project-URL: Documentation, https://github.com/gweidart/rs-bpe#readme
Project-URL: Bug Tracker, https://github.com/gweidart/rs-bpe/issues
